renovation/__init__.py
renovation/__main__.py
renovation/constants.py
renovation/floor_plan.py
renovation/project.py
renovation/elements/__init__.py
renovation/elements/basic.py
renovation/elements/electricity.py
renovation/elements/element.py
renovation/elements/info.py
renovation/elements/lighting.py
renovation/elements/multipurpose.py
renovation/elements/registry.py
renovation-0.1.1.dist-info/LICENSE
renovation-0.1.1.dist-info/METADATA
renovation-0.1.1.dist-info/WHEEL
renovation-0.1.1.dist-info/top_level.txt
renovation-0.1.1.dist-info/RECORD
