Metadata-Version: 2.1
Name: renovation
Version: 0.1.1
Summary: Drawing tool that produces floor plans needed to renovate an apartment
Author-email: Nikolay Lysenko <nikolay-lysenco@yandex.ru>
Project-URL: Homepage, https://github.com/Nikolay-Lysenko/renovation
Keywords: apartments,drawing,floor_plan,floor_plans
Classifier: Development Status :: 4 - Beta
Classifier: Intended Audience :: End Users/Desktop
Classifier: Topic :: Multimedia :: Graphics
Classifier: License :: OSI Approved :: MIT License
Classifier: Programming Language :: Python :: 3
Requires-Python: >=3.8
License-File: LICENSE
Requires-Dist: matplotlib
Requires-Dist: numpy
Requires-Dist: PyYAML
